statistical_clear_sky/__init__.py
statistical_clear_sky/configuration.py
statistical_clear_sky/dataviewer.py
statistical_clear_sky/algorithm/__init__.py
statistical_clear_sky/algorithm/exception.py
statistical_clear_sky/algorithm/iterative_fitting.py
statistical_clear_sky/algorithm/initialization/__init__.py
statistical_clear_sky/algorithm/initialization/linearization_helper.py
statistical_clear_sky/algorithm/initialization/singular_value_decomposition.py
statistical_clear_sky/algorithm/initialization/weight_setting.py
statistical_clear_sky/algorithm/minimization/__init__.py
statistical_clear_sky/algorithm/minimization/abstract.py
statistical_clear_sky/algorithm/minimization/left_matrix.py
statistical_clear_sky/algorithm/minimization/right_matrix.py
statistical_clear_sky/algorithm/minimization/right_matrix_no_constraints.py
statistical_clear_sky/algorithm/plot/__init__.py
statistical_clear_sky/algorithm/plot/plot_mixin.py
statistical_clear_sky/algorithm/serialization/__init__.py
statistical_clear_sky/algorithm/serialization/serialization_mixin.py
statistical_clear_sky/algorithm/serialization/state_data.py
statistical_clear_sky/utilities/__init__.py
statistical_clear_sky/utilities/data_conversion.py
statistical_clear_sky/utilities/data_loading.py
statistical_clear_sky/utilities/filters.py
statistical_clear_sky/utilities/progress.py
tests/statistical_clear_sky/__init__.py
tests/statistical_clear_sky/algorithm/__init__.py
tests/statistical_clear_sky/algorithm/test_iterative_fitting.py
tests/statistical_clear_sky/algorithm/test_iterative_fitting_execute.py
tests/statistical_clear_sky/algorithm/initialization/__init__.py
tests/statistical_clear_sky/algorithm/initialization/test_linearization_helper.py
tests/statistical_clear_sky/algorithm/initialization/test_singular_value_decomposition.py
tests/statistical_clear_sky/algorithm/initialization/test_weight_setting.py
tests/statistical_clear_sky/algorithm/minimization/__init__.py
statistical_clear_sky-0.4.6.dist-info/LICENSE
statistical_clear_sky-0.4.6.dist-info/METADATA
statistical_clear_sky-0.4.6.dist-info/WHEEL
statistical_clear_sky-0.4.6.dist-info/entry_points.txt
statistical_clear_sky-0.4.6.dist-info/top_level.txt
statistical_clear_sky-0.4.6.dist-info/RECORD
