Metadata-Version: 2.1
Name: statistical-clear-sky
Version: 0.4.6
Summary: Statistical estimation of a clear sky signal from PV system power data
Home-page: https://github.com/bmeyers/StatisticalClearSky
Author: SLAC National Accelerator Laboratory - Bennet Meyers
Author-email: bennetm@stanford.edu
License: UNKNOWN
Project-URL: Bug Reports, https://github.com/bmeyers/StatisticalClearSky/issues
Keywords: solar pv photovoltaic
Platform: UNKNOWN
Classifier: Development Status :: 3 - Alpha
Classifier: Intended Audience :: Science/Research
Classifier: Topic :: Scientific/Engineering
Classifier: License :: OSI Approved :: BSD License
Classifier: Programming Language :: Python :: 3
Classifier: Programming Language :: Python :: 3.6
Classifier: Programming Language :: Python :: 3.7
Requires-Python: >=3.6, <4
Requires-Dist: cmake
Requires-Dist: cvxpy (>=1.0)
Requires-Dist: matplotlib
Requires-Dist: numpy (==1.22.0)
Requires-Dist: pandas
Requires-Dist: seaborn
Requires-Dist: solar-data-tools
Provides-Extra: dev
Requires-Dist: check-manifest ; extra == 'dev'
Provides-Extra: test
Requires-Dist: coverage ; extra == 'test'
